helical_thread/__init__.py
helical_thread/helicalthread.py
helical_thread-0.2.2.dist-info/AUTHORS.rst
helical_thread-0.2.2.dist-info/LICENSE
helical_thread-0.2.2.dist-info/METADATA
helical_thread-0.2.2.dist-info/WHEEL
helical_thread-0.2.2.dist-info/top_level.txt
helical_thread-0.2.2.dist-info/RECORD
