Metadata-Version: 2.1
Name: helical-thread
Version: 0.2.2
Summary: Creates a helical thread
Home-page: https://github.com/winksaville/py-helical-thread
Author: Wink Saville
Author-email: wink@saville.com
License: MIT
Keywords: helical helix thread
Platform: any
Classifier: Development Status :: 2 - Pre-Alpha
Classifier: Intended Audience :: Developers
Classifier: License :: OSI Approved :: MIT License
Classifier: Natural Language :: English
Classifier: Operating System :: OS Independent
Classifier: Programming Language :: Python :: 3.7
Classifier: Programming Language :: Python :: 3.8
Requires-Python: >=3.7
Requires-Dist: taperable-helix
